var alminhas={"type":"FeatureCollection","features":[{"type":"Feature","geometry":{"type":"Point","coordinates":[-7.7523427,40.6292867,0]},"properties":{"name":"Oliveira, Rua da Escola","FICHA INVENTÁRIO":"0126-MAN-VS","FREGUESIA":"Mangualde","PAINEL":"Não","LAT":40.6292867,"LONG":-7.7523427,"DESCRIÇÃO DO ORATÓRIO":"Alminhas em granito, tipo estela, de formato retangular e topo redondo, inserido num muro a três quartos do seu corpo. Edícula emoldurada de topo redondo, rematada por cruz relevada, de extremidades trilobadas. Abaixo, uma cartela ovalada.","OBS":"https://docs.google.com/document/d/e/2PACX-1vR1VGRRxxfmtZhT2ji3vIoKcLoj32Vadbx42ilSerKXX7m1YMLSfMomUekB-i8ZDcywQMbTgFgyRaVa/pub","gx_media_links":"https://doc-0s-ag-mymaps.googleusercontent.com/untrusted/hostedimage/rkqv29me7hi5r9bt90grkt698g/p4domnhrtvqltmiquj142blrjs/1646505766750/3evDZZ2F1ONbZ8Mo7WuI6QKm2vmYGVzF/00061990690341275947/5AIsG_vZqI_u_3l0HX7KqGJLjmtf7gqpqoqu9AqbAxkBlC_PFvMOP3qmrWYhuMAocKRXlh0kBBb-jtRuFxWLnzrT9Eq7araQkf4hE2GF0Kj_ucD5qZKPsdqhPhzbk6286zwtWzzR29LQ-Ss1KVfjLu4kP3mf-XdR7nqhBbGuF-9vNm103-zRXMCj85asuWGPqjaPMBhc?session=0&fife"}}]};
